map_poster_creator/__init__.py
map_poster_creator/color_schemes.py
map_poster_creator/config.py
map_poster_creator/entrypoints.py
map_poster_creator/geojson.py
map_poster_creator/logs.py
map_poster_creator/main.py
map_poster_creator/plotting.py
map_poster_creator-0.8.dist-info/LICENSE
map_poster_creator-0.8.dist-info/METADATA
map_poster_creator-0.8.dist-info/WHEEL
map_poster_creator-0.8.dist-info/entry_points.txt
map_poster_creator-0.8.dist-info/top_level.txt
map_poster_creator-0.8.dist-info/RECORD
