Metadata-Version: 2.1
Name: map-poster-creator
Version: 0.8
Summary: Map Poster Creator
Home-page: https://github.com/k4m454k/MapPosterCreator
Author: Vadim Apenko
Author-email: k4m454k@gmail.com
License: UNKNOWN
Platform: UNKNOWN
Requires-Python: >=3.7
Requires-Dist: geopandas
Requires-Dist: shapely
Requires-Dist: matplotlib
Requires-Dist: descartes
